{
  "판례일련번호": "157588",
  "사건명": "공직 선거법 위반",
  "사건번호": "2010도16996",
  "법원명": "대법원",
  "사건유형": "",
  "판결유형": "판결",
  "선고일자": "20110310",
  "판시사항": "[1]공직선거법 제89조 제2항 본문 후단에서 정한 ‘그 명의를 유추할 수 있는 방법으로’ 선전하는 행위의 의미 및 벽보 등을 이용한 단체 등의 선전행위가 정당이나 후보자의 명의를 쉽게 유추할 수 있는 방법에 해당하는지를 판단하는 기준(=일반 선거구민)<br/>[2] 석산 개발을 반대하거나 지하철 유치 예비타당성 검토방침을 환영한다는 취지의 본문과 함께 지방선거에 출마한 후보자가 설립한 추진위원회와 그 후보자가 개설한 인터넷카페의 명칭 및 그 카페 인터넷주소가 표시된 현수막을 게시한 사안에서, 위 현수막이 후보자의 명의를 유추할 수 있는 방법으로 이용되지 않았다고 본 원심판단을 수긍한 사례<br/>[3] 지방선거에 출마한 후보자가 입후보 전 자신이 설립한 추진위원회 회원 등을 통해 후보자의 성명과 사진이 들어있는 추진위원회 명의의 전단지를 선거구민들에게 배부한 사안에서, 전단지 배부 당시 후보자가 이미 지방선거에 입후보할 의사를 갖고 있었던 점 등에 비추어 전단지 배부행위는 사전선거운동 및 탈법적 문서배부행위에 해당한다고 본 원심판단을 수긍한 사례<br/>",
  "판결요지": "",
  "판결본문": "",
  "참조조문": "[1]공직선거법 제89조 제2항 / [2]공직선거법 제89조 제2항 / [3]공직선거법 제93조 제1항,제254조 제2항,제255조 제2항 제5호<br/>",
  "참조판례": ""
}