{
  "판례일련번호": "157647",
  "사건명": "소유 이전 등기 말소등·부당 이득금 반환",
  "사건번호": "2010다37325,37332",
  "법원명": "대법원",
  "사건유형": "",
  "판결유형": "판결",
  "선고일자": "20110908",
  "판시사항": "甲의 대리인 乙이, 토지 소유자인 丙에게서 매도에 관한 대리권을 위임받지 않았음에도 대리인이라고 사칭한 丁으로부터 토지를 매수하기로 하는 매매계약을 체결한 후, 甲이 丙 명의 계좌로 매매대금을 송금하였는데, 丙에게서 미리 통장과 도장을 교부받아 소지하고 있던 丁이 위 돈을 송금당일 전액 인출한 사안에서, 丙이 위 돈을 송금 받아 실질적으로 이익의 귀속자가 되었다고 보기 어렵다고 하며, 甲의 부당이득반환청구를 인용한 원심판결에는 법리오해의 위법이 있다고 한 사례<br/>",
  "판결요지": "甲의 대리인 乙이, 토지의 소유자인 丙에게서 매도에 관한 대리권을 위임받지 않았음에도 대리인이라고 사칭한 丁으로부터 토지를 매수하기로 하는 매매계약을 체결하였고 이에 기하여 甲이 丙 명의의 계좌로 매매대금을 송금하였는데, 丙에게서 미리 통장과 도장을 교부받아 소지하고 있던 丁이 위 돈을 송금당일 전액 인출한 사안에서, 甲이 송금한 돈이 丙의 계좌로 입금되었다고 하더라도, 그로 인하여 丙이 위 돈 상당을 이득하였다고 하기 위해서는 丙이 이를 사실상 지배할 수 있는 상태에까지 이르러 실질적인 이득자가 되었다고 볼 만한 사정이 인정되어야 할 것인데, 甲의 송금 경위 및 丁이 이를 인출한 경위 등에 비추어 볼 때 丙이 위 돈을 송금 받아 실질적으로 이익의 귀속자가 되었다고 보기 어렵다고 하며, 甲의 부당이득반환청구를 인용한 원심판결에는 부당이득에 관한 법리오해의 위법이 있다고 한 사례.<br/>",
  "판결본문": "",
  "참조조문": "민법 제741조<br/>",
  "참조판례": ""
}