{
  "판례일련번호": "165557",
  "사건명": "부당이득금반환",
  "사건번호": "2011다79210",
  "법원명": "대법원",
  "사건유형": "",
  "판결유형": "판결",
  "선고일자": "20120329",
  "판시사항": "[1] 집합건물 건축자가 자기 소유의 대지 위에 집합건물을 건축하고 전유부분에 관하여 건축자 명의의 소유권보존등기가 마쳐진 경우, 건축자의 대지소유권이           집합건물의 소유 및 관리에 관한 법률 제2조 제6호에서 정한 대지사용권에 해당하는지 여부(적극) 및 건축자의 대지소유권에 관하여 부동산등기법에 따른 대지권등기가 마쳐지지 않은 상태에서 전유부분에 관한 경매절차에서 전유부분을 매수한 매수인이 대지사용권을 취득하는지 여부(원칙적 적극)        <br/>[2] 집합건물 건축자로부터 전유부분과 대지지분을 함께 분양 형식으로 대물변제받았으나 전유부분에 관하여만 소유권이전등기를 마친 경우, 전유부분 소유자가 대지사용권을 취득하는지 여부(적극) 및 위 전유부분 소유자로부터 전유부분과 대지지분을 매수한 양수인도 대지사용권을 취득하는지 여부(적극)<br/>",
  "판결요지": "",
  "판결본문": "",
  "참조조문": "[1]         집합건물의 소유 및 관리에 관한 법률 제2조 제6호,         제20조 제1항,         제2항 / [2]         집합건물의 소유 및 관리에 관한 법률 제2조 제6호,         제20조 제1항,         제2항<br/>",
  "참조판례": "[1]         대법원 2001. 9. 4. 선고 2001다22604 판결(공2001하, 2170),         대법원 2008. 9. 11. 선고 2007다45777 판결(공2008하, 1355) / [2]         대법원 2000. 11. 16. 선고 98다45652, 45669 전원합의체 판결(공2001상, 39)      <br/>"
}