{
  "판례일련번호": "172059",
  "사건명": "의료법 위반",
  "사건번호": "2013도8032",
  "법원명": "대법원",
  "사건유형": "",
  "판결유형": "판결",
  "선고일자": "20131212",
  "판시사항": "의사인 피고인이 자신이 운영하는 병원에서 VBAC(브이백) 시술을 받은 환자들이 병원 홈페이지에 그 성공소감을 게시하면 분만비를 할인해 주는 방법으로 의료광고를 하였다고 하여 의료법 위반으로 기소된 사안에서, 브이백 시술은 치료에 해당하고, 그 경험담은 의료법 시행령 제23조 제1항 제2호에서 금지하는 ‘환자의 치료경험담’으로서, 피고인의 행위는 의료광고에 해당한다고 한 사례<br/>",
  "판결요지": "의사인 피고인이 자신이 운영하는 병원에서 VBAC(Vaginal Birth After Cesarean, 제왕절개 후 자연분만, 이하 ‘브이백’이라 한다) 시술을 받은 환자들이 병원 홈페이지에 그 성공소감을 게시하면 분만비를 할인해 주는 방법으로 의료광고를 하였다고 하여 의료법 위반으로 기소된 사안에서, 의료법령상 ‘질병’이나 ‘치료’에 관하여 정의를 내리고 있는 법조문이 없어 구체적 사안에 따라 사회통념에 의하여 정할 수밖에 없는데, ‘치료’라는 표현이 좁은 의미의 질병에 대한 의료행위만을 의미하는 용어로 사용되고 있다고 보기 어려운 점, 일반적으로 출산을 앞둔 산모의 상태를 질병으로 분류하기 어렵다고 하더라도 미용성형이나 모발이식수술 등을 받는 사람과 달리 산모는 일반적인 상태에서 벗어난 비정상적인 건강상태에 있다고 할 수 있고, 특히 제왕절개 경험이 있는 산모가 자연분만을 시도하는 경우에는 그렇지 않은 경우에 비하여 산모나 태아의 생명, 신체에 위험을 초래할 가능성이 높아 전문 의료인에 의한 특별한 관리와 검사, 시술이 요구되는 점 등을 고려하면 그러한 상태에 있는 산모의 출산을 돕는 브이백 시술은 치료에 해당하고, 그 경험담은 의료법 시행령 제23조 제1항 제2호에서 금지하는 ‘환자의 치료경험담’으로서 시술이 갖는 위험성과 경험담의 구체적 내용에 비추어 볼 때, 소비자를 현혹하거나 국민건강에 중대한 위해를 발생하게 할 우려가 있는 의료광고에 해당한다고 한 사례.<br/>",
  "판결본문": "",
  "참조조문": "의료법 제56조 제2항 제2호, 제11호, 제5항, 제89조, 의료법 시행령 제23조 제1항 제2호<br/>",
  "참조판례": ""
}