{
  "판례일련번호": "174105",
  "사건명": "정치자금법위반·공직선거법위반·특정경제범죄가중처벌등에관한법률위반(사기)",
  "사건번호": "2013도7876",
  "법원명": "대법원",
  "사건유형": "",
  "판결유형": "판결",
  "선고일자": "20130926",
  "판시사항": "[1] 정당의 후보자추천 관련 금품수수 금지를 규정한 공직선거법 제47조의2 제1항에서 ‘후보자로 추천하는 일과 관련하여’의 의미<br/> [2] 국회의원 선거에서 정당의 공천을 받게 하여 줄 의사나 능력이 없음에도 이를 해 줄 수 있는 것처럼 기망하여 공천과 관련하여 금품을 받은 경우, 그 죄책 및 죄수 관계(=공직선거법상 공천 관련 금품수수죄와 사기죄의 상상적 경합범)<br/> [3] 공직선거에서 특정인을 후보자로 추천하는 행위와 관련하여 수수된 금전이 정치활동을 위하여 제공된 것이 아닌 경우, 정치자금법 제45조 제1항 위반죄가 성립하는지 여부(소극)<br/>",
  "판결요지": "",
  "판결본문": "",
  "참조조문": "[1] 공직선거법 제47조의2 제1항, 제230조 제6항 / [2] 형법 제40조, 제347조, 공직선거법 제47조의2 제1항, 제230조 제6항 / [3] 정치자금법 제3조 제1호, 제32조 제1호, 제45조 제1항<br/>",
  "참조판례": "[1][2] 대법원 2009. 4. 23. 선고 2009도834 판결(공2009상, 808) / [1] 대법원 2007. 9. 6. 선고 2006도6307 판결 / [3] 대법원 1999. 3. 23. 선고 99도404 판결(공1999상, 813), 대법원 2007. 7. 12. 선고 2007도2222 판결<br/>"
}