{
  "판례일련번호": "179097",
  "사건명": "구상금",
  "사건번호": "2014다88215",
  "법원명": "대법원",
  "사건유형": "",
  "판결유형": "판결",
  "선고일자": "20150528",
  "판시사항": "[1] 운송주선업자가 운송의뢰인으로부터 운송까지 의뢰받은 것인지 운송주선만을 의뢰받은 것인지 불명확한 경우의 판단 기준<br/>[2] 상업송장이 상법 제797조 제3항 본문의 ‘그 밖에 운송계약을 증명하는 문서’에 해당하는지 여부(소극)<br/>",
  "판결요지": "",
  "판결본문": "",
  "참조조문": "[1] 상법 제114조, 제125조 / [2] 상법 제797조 제1항, 제2항, 제3항<br/>",
  "참조판례": "[1] 대법원 2007. 4. 27. 선고 2007다4943 판결(공2007상, 783), 대법원 2012. 12. 27. 선고 2011다103564 판결 / [2] 대법원 2000. 11. 10. 선고 99다8315 판결, 대법원 2003. 1. 24. 선고 2002다53667 판결<br/>"
}