{
  "판례일련번호": "180323",
  "사건명": "재산세등부과처분취소",
  "사건번호": "2015두40958",
  "법원명": "대법원",
  "사건유형": "",
  "판결유형": "판결",
  "선고일자": "20160218",
  "판시사항": "종중이 구 지방세특례제한법 제50조 제2항에서 정한 ‘제사를 목적으로 하는 단체’에 포함되는지 여부(소극)<br/>",
  "판결요지": "구 지방세특례제한법(2014. 1. 1. 법률 제12175호로 개정되기 전의 것) 제50조 제2항(이하 ‘감면조항’이라고 한다)은 ‘종교 및 제사를 목적으로 하는 단체가 과세기준일 현재 해당 사업에 직접 사용하는 부동산에 대하여는 재산세 및 지역자원시설세를 각각 면제한다’고 규정하고 있다.<br/>  감면조항은 특정인이나 특정집단이 아닌 불특정 다수인의 이익을 위하여 다중의 보편적 문화를 지원하는 차원에서 지방세 감면혜택을 부여하는 데에 취지가 있는 점, 감면조항의 내용이나 체계에 비추어 볼 때 해당 규정의 제사는 불특정 다수인에게 개방된 종교와 유사한 사회적 기능과 역할을 수행하고 단체는 그러한 성격의 제사를 주된 목적으로 할 것을 전제한다고 보아야 하는 점, 반면 종중이 봉행하는 공동선조의 제사는 조상숭배의 사상에 바탕을 둔 우리의 특유한 관습으로서 보존가치가 있는 전통문화이기는 하지만 주된 기능과 역할이 특정한 범위의 후손들을 위한 것에 그치는 점, 종중은 공동선조의 제사뿐만 아니라 공동선조의 분묘수호와 종중 재산의 보존·관리, 종원 상호 간의 친목 등 다양한 목적을 위하여 구성되는 자연발생적인 종족집단이므로 제사만을 목적으로 한다고 보기도 어려운 점 등을 종합하면, 종중은 목적과 본질에 비추어 볼 때 일부 제사 시설을 보유하고 선조의 제사를 봉행하더라도 ‘제사를 목적으로 하는 단체’에 포함되지 아니한다.<br/>",
  "판결본문": "",
  "참조조문": "구 지방세특례제한법(2014. 1. 1. 법률 제12175호로 개정되기 전의 것) 제50조 제2항<br/>",
  "참조판례": ""
}