{
  "판례일련번호": "181695",
  "사건명": "업무상과실치사·업무상과실치상·산업안전보건법위반",
  "사건번호": "2015도8621",
  "법원명": "대법원",
  "사건유형": "",
  "판결유형": "판결",
  "선고일자": "20160324",
  "판시사항": "[1] 구 산업안전보건법 제29조 제3항에서 말하는 ‘제1항에 따른 사업주’의 의미<br/>[2] 구 산업안전보건법 제29조 제1항의 취지 / 위 조항의 ‘같은 장소에서 행하여지는 사업’의 의미 및 장소적 동일성 외에 시간적 동일성까지 필요한지 여부(소극)<br/>",
  "판결요지": "[1] 구 산업안전보건법(2013. 6. 12. 법률 제11882호로 개정되기 전의 것, 이하 같다) 제29조 제3항은 “제1항에 따른 사업주는 그의 수급인이 사용하는 근로자가 고용노동부령으로 정하는 산업재해 발생위험이 있는 장소에서 작업을 할 때에는 고용노동부령으로 정하는 산업재해 예방을 위한 조치를 하여야 한다.”라고 규정하고 있는데, 여기서 말하는 ‘제1항에 따른 사업주’란 구 산업안전보건법 제29조 제1항에 규정된 ‘같은 장소에서 행하여지는 사업으로서 사업의 일부를 분리하여 도급을 주어 하는 사업 중 대통령령으로 정하는 사업의 사업주’를 의미한다.<br/>[2] 구 산업안전보건법(2013. 6. 12. 법률 제11882호로 개정되기 전의 것, 이하 같다) 제29조 제1항은 사업의 일부를 도급한 발주자 또는 사업의 전부를 도급받아 그중 일부를 하도급에 의하여 행하는 수급인 등 사업의 전체적인 진행과정을 총괄하고 조율할 능력이나 의무가 있는 사업주에게 그가 관리하는 작업장에서 발생할 수 있는 산업재해를 예방하기 위한 조치를 하여야 할 의무를 규정한 조항으로, 구 산업안전보건법 제29조 제1항의 ‘같은 장소에서 행하여지는 사업’은 사업주와 그의 수급인이 같은 장소에서 작업을 하는 사업을 의미하고, 장소적 동일성 외에 시간적 동일성까지 필요하다고 볼 수 없다.<br/>",
  "판결본문": "",
  "참조조문": "[1] 구 산업안전보건법(2013. 6. 12. 법률 제11882호로 개정되기 전의 것) 제29조 제1항, 제3항, 제68조 제2호 / [2] 구 산업안전보건법(2013. 6. 12. 법률 제11882호로 개정되기 전의 것) 제29조 제1항<br/>",
  "참조판례": "[1] 대법원 2008. 7. 10. 선고 2007도5782 판결, 대법원 2009. 5. 28. 선고 2008도7030 판결(공2009하, 1051)<br/>"
}