{
  "판례일련번호": "182376",
  "사건명": "분양대금반환등·분양대금반환등·분양대금반환등",
  "사건번호": "2015다207679, 207686, 207693",
  "법원명": "대법원",
  "사건유형": "",
  "판결유형": "판결",
  "선고일자": "20151210",
  "판시사항": "[1] 매매계약이 매수인의 귀책사유로 해제되어 매매대금 증 일부가 위약금으로 몰취되는 경우, 매도인이 매수인에게 위약금에 대한 이자 상당액을 지급할 의무가 있는지 여부(소극)<br/>[2] 단순병합으로 구하여야 할 수개의 청구를 주위적·예비적 청구로 병합하여 청구하는 것이 허용되는지 여부(소극) 및 법원이 그중 하나의 청구만을 인용하고 나머지 청구를 기각하는 내용의 판결을 하고 피고만이 상고한 경우, 상고심의 심판 범위(=피고가 불복한 청구)<br/>",
  "판결요지": "",
  "판결본문": "",
  "참조조문": "[1] 민법 제548조 제2항 / [2] 민사소송법 제253조<br/>",
  "참조판례": "[2] 대법원 2008. 12. 11. 선고 2005다51471 판결<br/>"
}