{
  "판례일련번호": "182878",
  "사건명": "공문서변조·변조공문서행사·사문서변조·변조사문서행사·특정경제범죄가중처벌등에관한법률위반(횡령)[인정된죄명:특정경제범죄가중처벌등에관한법률위반(배임)]·특정경제범죄가중처벌등에관한법률위반(배임)·특정범죄가중처벌등에관한법률위반(허위세금계산서교부등)·범죄수익은닉의규제및처벌등에관한법률위반",
  "사건번호": "2014도11042",
  "법원명": "대법원",
  "사건유형": "",
  "판결유형": "판결",
  "선고일자": "20151223",
  "판시사항": "[1] 특정경제범죄 가중처벌 등에 관한 법률 제3조 제1항의 ‘이득액’의 의미<br/>[2] 범죄수익은닉의 규제 및 처벌 등에 관한 법률 제3조 제1항 제2호에 정한 ‘범죄수익의 발생 원인에 관한 사실을 가장’하는 행위의 의미 및 그러한 행위는 범죄수익을 발생시키는 범죄행위와 별도의 행위이어야 하는지 여부(적극)<br/>",
  "판결요지": "",
  "판결본문": "",
  "참조조문": "[1] 특정경제범죄 가중처벌 등에 관한 법률 제3조 제1항 / [2] 범죄수익은닉의 규제 및 처벌 등에 관한 법률 제3조 제1항 제2호<br/>",
  "참조판례": "[1] 대법원 2006. 5. 26. 선고 2006도1614 판결(공2006하, 1224), 대법원 2008. 6. 12. 선고 2008도2236 판결 / [2] 대법원 2014. 9. 4. 선고 2014도4408 판결(공2014하, 2085)<br/>"
}