{
  "판례일련번호": "192557",
  "사건명": "손해배상(기)",
  "사건번호": "2011다68357",
  "법원명": "대법원",
  "사건유형": "",
  "판결유형": "판결",
  "선고일자": "20141127",
  "판시사항": "[1] 과실상계 또는 책임제한에 관한 사실인정이나 비율을 정하는 기준 및 이때 가해자의 손해배상책임을 면제할 수 있는지 여부(원칙적 소극)<br/>[2] 甲 은행의 지점장이던 乙이 내규를 위반하여 사업부지에 관한 수익권증서를 담보로 丙 주식회사에 대출을 하였는데, 丙 회사가 거래정지처분을 받자 甲 은행이 위 대출채권에 대한 책정가액을 정하여 수익권증서 등과 함께 매각하였고, 그 후 위 사업부지가 대출채권을 초과하는 금액에 매각되자 甲 은행이 乙을 상대로 손해배상을 구한 사안에서, 乙의 손해배상책임을 면제한 원심판결에 법리오해의 잘못이 있다고 한 사례<br/>",
  "판결요지": "[1] 과실상계 또는 책임제한에 관한 사실인정이나 비율을 정하는 것이 사실심의 전권사항이라고 하더라도, 그것이 형평의 원칙에 비추어 불합리하여서는 아니 되며, 특히 가해자의 손해배상책임을 면제하는 것은 실질적으로 가해자의 손해배상책임을 부정하는 것과 다름이 없으므로, 불법행위로 인한 피해자의 손해가 실질적으로 전부 회복되었다거나 손해를 전적으로 피해자에게 부담시키는 것이 합리적이라고 볼 수 있는 등의 특별한 사정이 없는 한 가해자의 책임을 함부로 면제하여서는 아니 된다.<br/>[2] 甲 은행의 지점장이던 乙이 내규를 위반하여 사업부지에 관한 수익권증서를 담보로 丙 주식회사에 대출을 하였는데, 丙 회사가 거래정지처분을 받자 甲 은행이 대출채권에 대한 책정가액을 정하여 담보인 수익권증서 등과 함께 이를 매각하였고, 그 후 위 사업부지가 위 대출채권을 초과하는 금액에 매각되자 甲 은행이 乙을 상대로 손해배상을 구한 사안에서, 위 사업부지가 대출채권을 초과하는 금액에 매각된 것은 대출채권을 매각한 때로부터 2년 8개월이 경과한 후로서 매각대금에는 사업부지에 대한 지가상승분이 반영된 것으로 보이고, 甲 은행이 대출채권을 매각할 무렵에는 책정가액보다 낮은 금액에도 매각되지 아니한 점 등에 비추어 보면, 乙의 손해배상책임을 감경하는 것에서 더 나아가 책임을 면제할 정도에 이른다고 볼 수 없음에도, 이와 달리 乙의 손해배상책임을 면제함이 상당하다고 본 원심판결에 법리오해의 잘못이 있다고 한 사례.<br/>",
  "판결본문": "",
  "참조조문": "[1] 민법 제396조, 제750조, 제763조 / [2] 민법 제396조, 제750조, 제763조<br/>",
  "참조판례": "[1] 대법원 2010. 10. 28. 선고 2010다52126 판결<br/>"
}