{
  "판례일련번호": "192757",
  "사건명": "소유권이전등기등",
  "사건번호": "2015다52589",
  "법원명": "대법원",
  "사건유형": "",
  "판결유형": "판결",
  "선고일자": "20170921",
  "판시사항": "위탁자가 금전채권을 담보하기 위하여 금전채권자를 우선수익자로, 위탁자를 수익자로 하여 위탁자 소유의 부동산을 신탁법에 따라 수탁자에게 이전하면서 채무불이행 시에는 이를 처분하여 위 채권의 변제 등에 충당하기로 하는 내용의 담보신탁을 한 경우, 금전채권이 제3자에게 양도 또는 전부되었다는 사정만으로 우선수익권이 수반하여 제3자에게 이전되거나 금전채권과 우선수익권의 귀속이 달라졌다는 이유만으로 우선수익권이 소멸하는지 여부(소극)<br/>",
  "판결요지": "위탁자가 금전채권을 담보하기 위하여 금전채권자를 우선수익자로, 위탁자를 수익자로 하여 위탁자 소유의 부동산을 신탁법에 따라 수탁자에게 이전하면서 채무불이행 시에는 신탁부동산을 처분하여 우선수익자의 채권 변제 등에 충당하고 나머지를 위탁자에게 반환하기로 하는 내용의 담보신탁을 해 둔 경우, 특별한 사정이 없는 한 우선수익권은 경제적으로 금전채권에 대한 담보로 기능할 뿐 금전채권과는 독립한 신탁계약상의 별개의 권리가 된다. 따라서 이러한 우선수익권과 별도로 금전채권이 제3자에게 양도 또는 전부되었다고 하더라도 그러한 사정만으로 우선수익권이 금전채권에 수반하여 제3자에게 이전되는 것은 아니고, 금전채권과 우선수익권의 귀속이 달라졌다는 이유만으로 우선수익권이 소멸하는 것도 아니다.<br/>",
  "판결본문": "",
  "참조조문": "구 신탁법(2011. 7. 25. 법률 제10924호로 전부 개정되기 전의 것) 제1조 제2항(현행 제2조 참조), 제51조 제1항(현행 제56조 제1항 참조), 민법 제361조, 제369조<br/>",
  "참조판례": "대법원 2017. 6. 22. 선고 2014다225809 전원합의체 판결(공2017하, 1534)<br/>"
}