{
  "판례일련번호": "195422",
  "사건명": "건축허가취소처분취소",
  "사건번호": "2017두50843",
  "법원명": "대법원",
  "사건유형": "",
  "판결유형": "판결",
  "선고일자": "20171026",
  "판시사항": "[1] 막다른 골목길을 유일한 통행로로 하는 부지에 대한 건축 허가 또는 신고나 준공검사가 있는 경우, 건축법 제44조 제1항 본문이 건축물 대지의 접도 요건을 규정하고 있다는 점만을 들어 위 골목길에 대한 도로로서의 위치 지정이 있었던 것으로 추정할 수 있는지 여부(소극)<br/>[2] 건축법 제44조 제1항이 건축물 대지의 접도 요건을 규정한 취지 및 같은 항 단서 제1호의 ‘해당 건축물의 출입에 지장이 없다고 인정되는 경우’에 해당하는지 판단하는 방법<br/>",
  "판결요지": "",
  "판결본문": "",
  "참조조문": "[1] 건축법 제2조 제1항 제11호, 제44조 제1항 / [2] 건축법 제44조 제1항 제1호<br/>",
  "참조판례": "[1] 대법원 1999. 2. 9. 선고 98두12802 판결(공1999상, 491) / [2] 대법원 1999. 6. 25. 선고 98두18299 판결(공1999하, 1527)<br/>"
}