{
  "판례일련번호": "204485",
  "사건명": "가격조정명령처분취소",
  "사건번호": "2016두64975",
  "법원명": "대법원",
  "사건유형": "",
  "판결유형": "판결",
  "선고일자": "20190131",
  "판시사항": "[1] 교과용도서에 관한 규정 제33조 제2항에서 정한 ‘각호의 사유로 검정도서와 인정도서의 가격이 부당하게 결정될 우려가 있다’는 이유로 가격 조정 명령을 하기 위한 요건 및 가격 조정 명령 대상 교과용 도서에 대하여 위 조항 각호의 사유가 인정되는 경우 곧바로 ‘그 교과용 도서의 가격이 부당하게 결정될 우려’가 추정되는지 여부(소극)<br/>[2] 행정청이 처분을 하면서 처분의 근거와 이유를 구체적으로 명시하지 않았으나 당사자가 그 근거를 알 수 있을 정도로 이유를 제시한 경우, 처분이 위법한지 여부(소극) 및 이때 ‘이유를 제시한 경우’의 의미<br/>",
  "판결요지": "[1] 교과용도서에 관한 규정 제33조 제2항의 문언 내용과 개정 연혁, 입법 취지 등에 비추어 보면, 위 조항에서 정한 ‘각호의 사유로 검정도서와 인정도서의 가격이 부당하게 결정될 우려가 있다’는 이유로 가격 조정 명령을 하기 위해서는, 해당 교과용 도서가 위 조항 각호의 사유에 해당함은 물론 그와 같은 사정 등으로 인하여 ‘가격이 부당하게 결정될 우려’가 있음이 별개로 인정되어야 한다. 이때 가격 조정 명령 대상 교과용 도서에 대하여 위 조항 각호의 사유가 인정된다고 하여, 곧바로 ‘그 교과용 도서의 가격이 부당하게 결정될 우려’가 추정되는 관계로 볼 수는 없다. 그 이유는 다음과 같다.<br/>  ① 가격이 부당하게 결정될 우려가 있는지 여부는 검·인정도서 출판사의 과다한 이득과 이로 인한 수요자의 경제적 부담 증가 등을 종합적으로 고려하여 판단하여야 한다. 위 조항 각호가 정한 사유가 있다고 하여 항상 출판사가 과다한 이득을 얻는다거나 그로 인하여 수요자의 경제적 부담이 증가한다고 단정하기 어렵다.<br/>  ② 위 조항 각호의 사유와 출판사가 실제로 결정한 가격 또는 희망하는 가격 사이의 상관관계가 명확하다고 보기 어렵다. 위 조항 각호의 사유가 있음에도 불구하고 출판사가 결정한 가격 또는 희망하는 가격 자체는 객관적으로 보아 부당한 가격이 아닐 수 있다.<br/>[2] 행정청이 처분을 할 때에는 원칙적으로 당사자에게 그 근거와 이유를 제시하여야 한다(행정절차법 제23조 제1항). 이 경우 행정청은 처분의 원인이 되는 사실과 근거가 되는 법령 또는 자치법규의 내용을 구체적으로 명시하여야 한다(행정절차법 시행령 제14조의2).<br/>  다만 행정청의 자의적 결정을 배제하고 당사자로 하여금 행정구제절차에서 적절히 대처할 수 있도록 하는 처분의 근거 및 이유제시 제도의 취지에 비추어, 처분을 하면서 당사자가 그 근거를 알 수 있을 정도로 이유를 제시한 경우에는 처분의 근거와 이유를 구체적으로 명시하지 않았더라도 그로 말미암아 그 처분이 위법하다고 볼 수는 없다. 이때 ‘이유를 제시한 경우’는 처분서에 기재된 내용과 관계 법령 및 당해 처분에 이르기까지의 전체적인 과정 등을 종합적으로 고려하여, 처분 당시 당사자가 어떠한 근거와 이유로 처분이 이루어진 것인지를 충분히 알 수 있어서 그에 불복하여 행정구제절차로 나아가는 데 별다른 지장이 없었다고 인정되는 경우를 뜻한다.<br/>",
  "판결본문": "",
  "참조조문": "[1] 교과용도서에 관한 규정 제33조 제1항, 제2항 / [2] 행정절차법 제23조 제1항, 행정절차법 시행령 제14조의2<br/>",
  "참조판례": "[2] 대법원 2017. 8. 29. 선고 2016두44186 판결(공2017하, 1867)<br/>"
}