{
  "판례일련번호": "204496",
  "사건명": "대여금등",
  "사건번호": "2013다14217",
  "법원명": "대법원",
  "사건유형": "",
  "판결유형": "판결",
  "선고일자": "20190131",
  "판시사항": "[1] 구 국가배상법 제2조 제1항에서 정한 ‘공무원’의 의미<br/>[2] 구 부동산소유권 이전등기 등에 관한 특별조치법상 보증인이 공무를 위탁받아 실질적으로 공무를 수행한다고 볼 수 있는지 여부(소극)<br/>",
  "판결요지": "[1] 구 국가배상법(2005. 7. 13. 법률 제7584호로 개정되기 전의 것) 제2조 제1항은 ‘국가 또는 지방자치단체는 공무원이 그 직무를 집행함에 당하여 고의 또는 과실로 법령에 위반하여 타인에게 손해를 가한 때에는 손해를 배상하여야 한다.’고 규정하였는데, 그 ‘공무원’이란 국가공무원법이나 지방공무원법에 의하여 공무원으로서 신분을 가진 자에 국한하지 않고, 널리 공무를 위탁받아 실질적으로 공무에 종사하고 있는 일체의 자를 가리킨다(현행 국가배상법 제2조 제1항은 ‘공무를 위탁받은 사인’도 공무원에 해당한다고 명시하고 있다).<br/>[2] 구 부동산소유권 이전등기 등에 관한 특별조치법(1992. 11. 30. 법률 제4502호, 실효, 이하 ‘구 특별조치법’이라 한다) 제7조 제1항, 제2항, 제10조 제2항, 제3항, 제11조, 구 부동산소유권 이전등기 등에 관한 특별조치법 시행령(1994. 8. 25. 대통령령 제14369호로 개정되기 전의 것) 제5조 내지 제9조, 제11조, 제12조 내지 제15조의 규정들을 종합하면, 구 특별조치법상 보증인은 공무를 위탁받아 실질적으로 공무를 수행한다고 보기는 어렵다. 보증인을 위촉하는 관청은 소정 요건을 갖춘 주민을 보증인으로 위촉하는 데 그치고 대장소관청은 보증서의 진위를 확인하기 위한 일련의 절차를 거쳐 확인서를 발급할 뿐 행정관청이 보증인의 직무수행을 지휘·감독할 수 있는 법령상 근거가 없으며, 보증인은 보증서를 작성할 의무를 일방적으로 부과받으면서도 어떠한 경제적 이익도 제공받지 못하는 반면 재량을 가지고 발급신청의 진위를 확인하며 그 내용에 관하여 행정관청으로부터 아무런 간섭을 받지 않기 때문이다.<br/>",
  "판결본문": "",
  "참조조문": "[1] 구 국가배상법(2005. 7. 13. 법률 제7584호로 개정되기 전의 것) 제2조 제1항 / [2] 구 국가배상법(2005. 7. 13. 법률 제7584호로 개정되기 전의 것) 제2조 제1항, 구 부동산소유권 이전등기 등에 관한 특별조치법(1992. 11. 30. 법률 제4502호, 실효) 제7조 제1항, 제2항, 제10조 제2항, 제3항, 제11조, 구 부동산소유권 이전등기 등에 관한 특별조치법 시행령(1994. 8. 25. 대통령령 제14369호로 개정되기 전의 것) 제5조(현행 삭제), 제6조(현행 삭제), 제7조(현행 삭제), 제8조(현행 삭제), 제9조(현행 삭제), 제11조(현행 삭제), 제12조(현행 삭제), 제13조(현행 삭제), 제14조(현행 삭제), 제15조(현행 삭제)<br/>",
  "참조판례": "[1] 대법원 1970. 11. 24. 선고 70다2253 판결(집18-3, 민326)<br/>"
}