{
  "판례일련번호": "204778",
  "사건명": "대여금",
  "사건번호": "2017다56967",
  "법원명": "대법원",
  "사건유형": "",
  "판결유형": "판결",
  "선고일자": "20180515",
  "판시사항": "민법 제63조에 의하여 법원이 선임한 임시이사의 권한 범위 및 법원의 임시이사 선임결정에 의하여 권리를 침해당한 자가 비송사건절차법 제20조에 따라 그 결정에 대하여 항고할 수 있는지 여부(적극)<br/>",
  "판결요지": "",
  "판결본문": "",
  "참조조문": "민법 제63조, 비송사건절차법 제20조<br/>",
  "참조판례": "대법원 1964. 8. 17. 선고 64마452 판결(집12-2, 민78), 대법원 2004. 10. 13.자 2004마718 결정, 대법원 2013. 6. 13. 선고 2012다40332 판결(공2013하, 1195), 대법원 2016. 6. 9. 선고 2016다8053 판결<br/>"
}