{
  "판례일련번호": "206306",
  "사건명": "국가보안법위반(찬양·고무등)·일반교통방해",
  "사건번호": "2014도14573",
  "법원명": "대법원",
  "사건유형": "",
  "판결유형": "판결",
  "선고일자": "20180830",
  "판시사항": "[1] 국가보안법상 ‘이적표현물’로 인정하기 위한 요건 및 표현물에 이적성이 있는지 판단하는 기준<br/>[2] 국가보안법 제7조 제5항의 죄가 목적범인지 여부(적극) 및 행위자에게 ‘이적행위를 할 목적’이 있었다는 점에 대한 증명책임 소재(=검사)와 증명 방법<br/>",
  "판결요지": "",
  "판결본문": "",
  "참조조문": "[1] 국가보안법 제7조 제5항 / [2] 국가보안법 제7조 제1항, 제5항, 형사소송법 제308조<br/>",
  "참조판례": "[1][2] 대법원 2010. 7. 23. 선고 2010도1189 전원합의체 판결(공2010하, 1696), 대법원 2013. 3. 28. 선고 2010도12836 판결, 대법원 2018. 1. 25. 선고 2016도18715 판결<br/>"
}