{
  "판례일련번호": "209177",
  "사건명": "마약류관리에관한법률위반(향정)·마약류관리에관한법률위반(대마)",
  "사건번호": "2015도13103",
  "법원명": "대법원",
  "사건유형": "",
  "판결유형": "판결",
  "선고일자": "20160830",
  "판시사항": "임시향정신성의약품으로 지정·공고된 물질을 수입한 자를 마약류 관리에 관한 법률 제58조 제1항 제3호에 의하여 처벌하기 위한 요건<br/>",
  "판결요지": "마약류 관리에 관한 법률(이하 ‘법’이라 한다) 제2조 제3호, 제3조 제5호, 제4조 제1항, 제5조 제3항, 제5조의2 제1항, 제2항, 제4항, 제5항, 제41조, 제47조, 제58조 제1항 제1호, 제3호, 제6호, 제7호, 제59조 제1항 제10호, 제60조 제1항 제3호의 규정 체계 및 법리와 아울러 임시마약류 지정 제도의 취지, 임시향정신성의약품과 법 제2조 제3호 (가)목에 해당하는 향정신성의약품 또는 이를 함유하는 향정신성의약품[이하 ‘(가)목의 향정신성의약품’이라 한다]의 실질적인 차이 등을 종합적으로 고려하여 보면, 임시향정신성의약품에 대하여 향정신성의약품에 준하여 취급·관리할 필요가 있다고 보아 일반 행위를 금지하는 제3조를 준용하는 데에서 더 나아가, 임시향정신성의약품으로 지정·공고된 물질을 수입한 자에 대하여 (가)목의 향정신성의약품에 대한 제3조 제5호 위반행위와 마찬가지로 보아 법정형이 무기 또는 5년 이상의 징역인 제58조 제1항 제3호 위반죄로 처벌하기 위하여는 임시향정신성의약품이 실질적으로 (가)목의 향정신성의약품에 준하는 물질에 해당하여야 한다고 제한적으로 해석함이 타당하다.<br/>  따라서 임시향정신성의약품이라도 (가)목의 향정신성의약품과 마찬가지로 중추신경계에 작용하고 오용하거나 남용할 경우 심한 신체적 또는 정신적 의존성이 있거나 적어도 그럴 우려가 충분하다는 요건을 갖추어야 법 제58조 제1항 제3호가 적용될 수 있으며, 그 요건에 대한 증명이 없는 경우에는 위 규정에 의하여 처벌할 수 없다.<br/>",
  "판결본문": "",
  "참조조문": "헌법 제12조 제1항, 형법 제1조 제1항, 마약류 관리에 관한 법률 제2조 제3호, 제3조 제5호, 제4조 제1항, 제5조 제3항, 제5조의2 제1항, 제2항, 제4항, 제5항, 제41조, 제47조, 제58조 제1항 제1호, 제3호, 제6호, 제7호, 제59조 제1항 제10호, 제60조 제1항 제3호, 약사법 제31조 제2항, 제3항<br/>",
  "참조판례": ""
}