{
  "판례일련번호": "209127",
  "사건명": "구상금",
  "사건번호": "2019다216435",
  "법원명": "대법원",
  "사건유형": "",
  "판결유형": "판결",
  "선고일자": "20190814",
  "판시사항": "채권자가 연대채무자 중 1인에 대하여 채무를 일부 면제하는 경우, 면제된 부담부분에 한하여 면제의 절대적 효력이 인정되는지 여부(원칙적 적극) 및 이때 채무 일부를 면제받은 연대채무자가 지급해야 할 잔존 채무액이 부담부분을 초과하는지 여부에 따라 다른 연대채무자의 채무에 미치는 영향<br/>",
  "판결요지": "민법 제419조는 “어느 연대채무자에 대한 채무면제는 그 채무자의 부담부분에 한하여 다른 연대채무자의 이익을 위하여 효력이 있다.”라고 정하여 면제의 절대적 효력을 인정한다. 이는 당사자들 사이에 구상의 순환을 피하여 구상에 관한 법률관계를 간략히 하려는 데 취지가 있는바, 채권자가 연대채무자 중 1인에 대하여 채무를 일부 면제하는 경우에도 그와 같은 취지는 존중되어야 한다. 따라서 연대채무자 중 1인에 대한 채무의 일부 면제에 상대적 효력만 있다고 볼 특별한 사정이 없는 한 일부 면제의 경우에도 면제된 부담부분에 한하여 면제의 절대적 효력이 인정된다고 보아야 한다. <br/>  구체적으로 연대채무자 중 1인이 채무 일부를 면제받는 경우에 그 연대채무자가 지급해야 할 잔존 채무액이 부담부분을 초과하는 경우에는 그 연대채무자의 부담부분이 감소한 것은 아니므로 다른 연대채무자의 채무에도 영향을 주지 않아 다른 연대채무자는 채무 전액을 부담하여야 한다. 반대로 일부 면제에 의한 피면제자의 잔존 채무액이 부담부분보다 적은 경우에는 차액(부담부분 - 잔존 채무액)만큼 피면제자의 부담부분이 감소하였으므로, 차액의 범위에서 면제의 절대적 효력이 발생하여 다른 연대채무자의 채무도 차액만큼 감소한다.<br/>",
  "판결본문": "",
  "참조조문": "민법 제419조<br/>",
  "참조판례": ""
}