{
  "판례일련번호": "214589",
  "사건명": "이혼",
  "사건번호": "2020므11658",
  "법원명": "대법원",
  "사건유형": "",
  "판결유형": "판결",
  "선고일자": "20210311",
  "판시사항": "동일한 수령대행인이 소송당사자 쌍방을 대신하여 소송서류를 동시에 송달받은 경우, 보충송달의 효력(원칙적 무효)<br/>",
  "판결요지": "보충송달제도는 본인 아닌 그의 사무원, 피용자 또는 동거인, 즉 수령대행인이 소송서류를 수령하여도 그의 지능과 객관적인 지위, 본인과의 관계 등에 비추어 사회통념상 본인에게 소송서류를 전달할 것이라는 합리적인 기대를 전제로 한다. 동일한 수령대행인이 이해가 대립하는 소송당사자 쌍방을 대신하여 소송서류를 동시에 수령하는 경우가 있을 수 있다. 이런 경우 수령대행인이 원고나 피고 중 한 명과도 이해관계의 상충 없이 중립적인 지위에 있기는 쉽지 않으므로 소송당사자 쌍방 모두에게 소송서류가 제대로 전달될 것이라고 합리적으로 기대하기 어렵다. 또한 이익충돌의 위험을 회피하여 본인의 이익을 보호하려는 데 취지가 있는 민법 제124조 본문에서의 쌍방대리금지 원칙에도 반한다. 따라서 소송당사자의 허락이 있다는 등의 특별한 사정이 없는 한, 동일한 수령대행인이 소송당사자 쌍방의 소송서류를 동시에 송달받을 수 없고, 그러한 보충송달은 무효라고 봄이 타당하다.<br/>",
  "판결본문": "",
  "참조조문": "민사소송법 제178조 제1항, 제183조 제1항, 제186조 제1항, 민법 제124조<br/>",
  "참조판례": "대법원 2016. 11. 10. 선고 2014다54366 판결(공2016하, 1895)<br/>"
}