{
  "판례일련번호": "219449",
  "사건명": "부당해고구제재심판정취소",
  "사건번호": "2020두40945",
  "법원명": "대법원",
  "사건유형": "",
  "판결유형": "판결",
  "선고일자": "20210708",
  "판시사항": "도급업체와 종전 용역업체의 계약기간이 만료되고 새로운 용역업체가 해당 업무를 위탁받아 용역계약을 체결하면서 종전 용역업체 소속 근로자에 대한 고용을 승계하여 새로운 근로관계가 성립될 것이라는 신뢰관계가 형성되어 근로자에게 고용승계에 대한 기대권이 인정되는 경우, 새로운 용역업체의 합리적 이유 없는 고용승계 거절의 효력(무효) 및 이때 근로자에게 고용승계에 대한 기대권이 인정되는지 판단하는 방법<br/>",
  "판결요지": "",
  "판결본문": "",
  "참조조문": "근로기준법 제23조<br/>",
  "참조판례": "대법원 2011. 4. 14. 선고 2007두1729 판결(공2011상, 925), 대법원 2016. 11. 10. 선고 2014두45765 판결(공2016하, 1930), 대법원 2021. 4. 29. 선고 2016두57045 판결(공2021상, 1081)<br/>"
}