{
  "판례일련번호": "238259",
  "사건명": "사기",
  "사건번호": "2018도3119",
  "법원명": "대법원",
  "사건유형": "",
  "판결유형": "판결",
  "선고일자": "20221229",
  "판시사항": "[1] 검사가 영장 발부의 사유로 된 범죄혐의사실과 무관한 별개의 증거를 압수하였을 경우, 이를 유죄 인정의 증거로 사용할 수 있는지 여부(원칙적 소극) / 이때 압수·수색의 목적이 된 범죄나 이와 관련된 범죄의 경우, 그 압수·수색의 결과를 유죄의 증거로 사용할 수 있는지 여부(적극)<br/>  [2] 전자문서를 수록한 파일 등의 증거능력을 인정하기 위한 요건 / 증거로 제출된 전자문서 파일의 사본이나 출력물이 복사·출력 과정에서 편집되는 등 인위적 개작 없이 원본 내용을 그대로 복사·출력한 것이라는 사실을 증명하는 방법<br/>",
  "판결요지": "",
  "판결본문": "",
  "참조조문": "[1] 형사소송법 제215조 제1항, 제307조 / [2] 형사소송법 제307조, 제308조<br/>",
  "참조판례": "[1] 대법원 2016. 3. 10. 선고 2013도11233 판결(공2016상, 587), 대법원 2019. 10. 17. 선고 2019도6775 판결, 대법원 2021. 7. 29. 선고 2020도14654 판결 / [2] 대법원 2013. 7. 26. 선고 2013도2511 판결(공2013하, 1659), 대법원 2016. 9. 28. 선고 2014도9903 판결, 대법원 2018. 2. 8. 선고 2017도13263 판결(공2018상, 595)<br/>"
}