{
  "판례일련번호": "239621",
  "사건명": "소송비용액확정",
  "사건번호": "2022마6636",
  "법원명": "대법원",
  "사건유형": "",
  "판결유형": "결정",
  "선고일자": "20221220",
  "판시사항": "[1] 민사소송에서 서로 대립하는 상대방이 없거나 형식상 상대방이 있더라도 상대방에게 공격 또는 방어할 수 있는 기회가 보장된 대심적 소송구조가 아닌 경우, 소송비용의 부담자 등을 정할 필요가 있는지 여부(소극)<br/>  [2] 가압류·가처분명령의 신청사건이 변론이나 심문 없이 진행된 경우, 변호사보수를 소송비용에 산입할 수 있는지 여부(소극) 및 가압류·가처분명령의 신청사건 항고심에서 변론 또는 심문기일이 열리기 전에 항고 취하로 사건이 종결되었더라도 변호사보수가 소송비용에 산입되는 경우 / 가압류·가처분명령의 신청사건에 대한 심리가 제1심 단계에서 변론 또는 심문을 거쳐 대심적 구조로 들어섰다고 하더라도 항고심에서 변론 또는 심문기일이 열리기 전에 항고인의 항고 취하로 사건이 종결되었고 그때까지 항고인의 상대방이 선임한 소송대리인이 항고이유에 대하여 답변서를 제출하는 등의 소송행위를 하지 않은 경우, 변호사보수가 소송비용에 산입될 수 있는지 여부(소극)<br/>",
  "판결요지": "",
  "판결본문": "",
  "참조조문": "[1] 민사소송법 제104조 / [2] 변호사보수의 소송비용 산입에 관한 규칙 제3조 제2항<br/>",
  "참조판례": "[1] 대법원 1985. 7. 9. 자 84카55 결정(공1985, 1299), 대법원 2019. 11. 29. 자 2019카확564 결정 / [2] 대법원 2010. 5. 25. 자 2010마181 결정, 대법원 2015. 9. 3. 자 2015마1043 결정<br/>"
}